AUTHORS.rst
CHANGELOG.rst
LICENSE
MANIFEST.in
README.rst
setup.py
django_generate.egg-info/PKG-INFO
django_generate.egg-info/SOURCES.txt
django_generate.egg-info/dependency_links.txt
django_generate.egg-info/not-zip-safe
django_generate.egg-info/requires.txt
django_generate.egg-info/top_level.txt
generate/__init__.py
generate/json_loader.py
generate/models.py
generate/management/__init__.py
generate/management/__init__.pyc
generate/management/commands/__init__.py
generate/management/commands/__init__.pyc
generate/management/commands/generate.py
generate/management/commands/generate.pyc
generate/management/commands/json_loader.py
generate/management/commands/json_loader.pyc
generate/resources/1.flv
generate/resources/1.jpg
generate/resources/2.jpg
generate/resources/3.jpg
generate/resources/4.jpg
generate/resources/5.jpg
generate/resources/6.jpg
generate/resources/7.jpg
generate/resources/blank_csv.csv
generate/resources/blank_pdf_document.pdf
generate/resources/blank_text_file.txt
generate/tests/__init__.py